fsm/__init__.py
fsm/core/__init__.py
fsm/core/action.py
fsm/core/automaton.py
fsm/core/interfaces.py
fsm/core/state.py
fsm_engine-0.1.0.dev3.dist-info/LICENSE.txt
fsm_engine-0.1.0.dev3.dist-info/METADATA
fsm_engine-0.1.0.dev3.dist-info/WHEEL
fsm_engine-0.1.0.dev3.dist-info/top_level.txt
fsm_engine-0.1.0.dev3.dist-info/RECORD
